netbom/__init__.py
netbom/bom.py
netbom/netlist.py
netbom/bom_readers/__init__.py
netbom/bom_readers/altium_bom_reader.py
netbom/netlist_readers/__init__.py
netbom/netlist_readers/rinf_netlist_reader.py
netbom-0.0.18.dist-info/LICENSE
netbom-0.0.18.dist-info/METADATA
netbom-0.0.18.dist-info/WHEEL
netbom-0.0.18.dist-info/entry_points.txt
netbom-0.0.18.dist-info/top_level.txt
netbom-0.0.18.dist-info/RECORD
