Metadata-Version: 2.1
Name: netbom
Version: 0.0.18
Summary: Library to read, convert and process electrical netlists and bill of materials generated in Altium Designer and KiCad.
Home-page: https://github.com/partmanager/netbom
Author: Piotr Kuligowski
Project-URL: Bug Tracker, https://github.com/partmanager/netbom/issues
Project-URL: Changelog, https://github.com/partmanager/netbom/releases
Project-URL: Source Code, https://github.com/partmanager/netbom
Project-URL: Documentation, https://partmanager.github.io/netbom
Classifier: Programming Language :: Python :: 3
Classifier: Intended Audience :: Developers
Classifier: Intended Audience :: Manufacturing
Classifier: License :: OSI Approved :: MIT License
Classifier: Operating System :: OS Independent
Requires-Python: >=3.8
License-File: LICENSE
Requires-Dist: openpyxl
Requires-Dist: pandas
